acsclient-1.0.8-py2.7-nspkg.pth
acsclient/acsclient.py
acsclient/templates/device.j2
acsclient/templates/devicegroup.j2
acsclient/templates/radius_device.j2
acsclient-1.0.8.dist-info/LICENSE
acsclient-1.0.8.dist-info/METADATA
acsclient-1.0.8.dist-info/WHEEL
acsclient-1.0.8.dist-info/namespace_packages.txt
acsclient-1.0.8.dist-info/pbr.json
acsclient-1.0.8.dist-info/top_level.txt
acsclient-1.0.8.dist-info/RECORD
