Metadata-Version: 2.1
Name: acsclient
Version: 1.0.8
Summary: Access Cisco ACS 5.6 API
Home-page: https://github.com/nlgotz/acsclient
Author: Nathan Gotz
Author-email: nathan@gotz.co
License: Apache 2.0
Keywords: cisco acs access control acsclient
Platform: UNKNOWN
Requires-Dist: requests
Requires-Dist: jinja2
Requires-Dist: MarkupSafe
